README
setup.py
chtMultiRegionFlux/__init__.py
chtMultiRegionFlux.egg-info/PKG-INFO
chtMultiRegionFlux.egg-info/SOURCES.txt
chtMultiRegionFlux.egg-info/dependency_links.txt
chtMultiRegionFlux.egg-info/entry_points.txt
chtMultiRegionFlux.egg-info/requires.txt
chtMultiRegionFlux.egg-info/top_level.txt
chtMultiRegionFlux.egg-info/zip-safe
chtMultiRegionFlux/r1_5/__init__.py
chtMultiRegionFlux/r1_5/coupleManager/__init__.py
chtMultiRegionFlux/r1_5/derivedFvPatchFields/__init__.py
chtMultiRegionFlux/r1_5/derivedFvPatchFields/solidWallHeatFluxTemperatureCoupledFvPatchScalarField.py
chtMultiRegionFlux/r1_5/derivedFvPatchFields/solidWallTemperatureCoupledFvPatchScalarField.py
chtMultiRegionFlux/r1_5/fluid/__init__.py
chtMultiRegionFlux/r1_5/regionProperties/__init__.py
chtMultiRegionFlux/r1_5/solid/__init__.py
chtMultiRegionFlux/r1_6/__init__.py
chtMultiRegionFlux/r1_6/derivedFvPatchFields/__init__.py
chtMultiRegionFlux/r1_6/fluid/__init__.py
chtMultiRegionFlux/r1_6/regionProperties/__init__.py
chtMultiRegionFlux/r1_6/solid/__init__.py
chtMultiRegionFlux/r1_6_dev/__init__.py
chtMultiRegionFlux/r1_6_dev/derivedFvPatchFields/__init__.py
chtMultiRegionFlux/r1_6_dev/fluid/__init__.py
chtMultiRegionFlux/r1_6_dev/regionProperties/__init__.py
chtMultiRegionFlux/r1_6_dev/solid/__init__.py
chtMultiRegionFlux/r1_7_0/__init__.py
chtMultiRegionFlux/r1_7_0/derivedFvPatchFields/__init__.py
chtMultiRegionFlux/r1_7_0/fluid/__init__.py
chtMultiRegionFlux/r1_7_0/regionProperties/__init__.py
chtMultiRegionFlux/r1_7_0/solid/__init__.py
chtMultiRegionFlux/r1_7_1/__init__.py
chtMultiRegionFlux/r1_7_1/derivedFvPatchFields/__init__.py
chtMultiRegionFlux/r1_7_1/fluid/__init__.py
chtMultiRegionFlux/r1_7_1/regionProperties/__init__.py
chtMultiRegionFlux/r1_7_1/solid/__init__.py
chtMultiRegionFlux/r2_0_0/__init__.py
chtMultiRegionFlux/r2_0_0/fluid/__init__.py
chtMultiRegionFlux/r2_0_0/solid/__init__.py
chtMultiRegionFlux/r2_1_0/__init__.py
chtMultiRegionFlux/r2_1_0/fluid/__init__.py
chtMultiRegionFlux/r2_1_0/solid/__init__.py
chtMultiRegionFlux/r2_1_1/__init__.py
chtMultiRegionFlux/r2_1_1/fluid/__init__.py
chtMultiRegionFlux/r2_1_1/solid/__init__.py